setup.cfg
setup.py
etsyapi/__init__.py
etsyapi.egg-info/PKG-INFO
etsyapi.egg-info/SOURCES.txt
etsyapi.egg-info/dependency_links.txt
etsyapi.egg-info/requires.txt
etsyapi.egg-info/top_level.txt