Metadata-Version: 1.1
Name: etsyapi
Version: 0.2.1
Summary: etsy.com api wrapper
Home-page: https://github.com/DempDemp/etsyapi
Author: Demp
Author-email: UNKNOWN
License: BSD
Download-URL: https://github.com/DempDemp/etsyapi/tarball/0.2.1
Keywords: etsy,api,etsy.com
Platform: UNKNOWN
